[
    {
        "header": "Week 1",
        "outcomes": "Alphabet, languages, and expressions",
        "CalendarInfo": " Dates: 3/28/22 - 4/1/22<br> Welcome! See you Monday in Warren Lecture Hall. Please take our <a href=\"https://forms.gle/gvibFnNixxqcWbaU8\" target=\"_blank\">pre-class survey.</a> ",
        "ExpandInCalendar": true,
        "content": [
            {
                "name": "Notes",
                "source": "Week1.tex"
            }, 
            {
                "name": "Lecture and Discussion podcast",
                "source": "<p>See <a href=\"https://podcast.ucsd.edu/watch/sp22/cse105_a00/1\">videos on podcast.ucsd.edu</a>"
            },
            {
                "name": "Lecture Hall",
                "source": "<br><iframe height=\"600px\" width=\"100%\" src=\"https://map.concept3d.com/?id=1005#!w/32.8738,-117.24095,0;32.88187,-117.23338,0;0\" frameborder=\"0\"></iframe>"
            },
            {
                "name": "(Video) Course Intro",
                "source": "https://www.youtube.com/embed/2KbOaCLS-cQ"
            }

        ],

        "Due Dates": [
            {
                "name": "Review Quiz",
                "link": "https://gradescope.com",
                "due": "10/1/21 at 5pm"
            }
        ]
    },
    {
        "header": "Finals week",
        "outcomes": "Final exam",
        "CalendarInfo":  "Dates: TBD. Final exam opens TBD. ",
        "ExpandInCalendar": true,
        "content": [
            {
                "name": "Final exam details",
                "source": "TBA"
            }
        ],
        "Due Dates": [
            {
                "name": "Final exam",
                "due": "TBA"
            }
        ]
    }
]